chessfluff/__init__.py
chessfluff/chessdotcom_api.py
chessfluff/config.py
chessfluff/lichess_api.py
chessfluff/logger.py
chessfluff/main.py
chessfluff/mappings.py
chessfluff/openings.py
chessfluff/requester.py
chessfluff/stockfish.py
chessfluff/utils.py
chessfluff-0.0.3.dist-info/WHEEL
chessfluff-0.0.3.dist-info/entry_points.txt
chessfluff-0.0.3.dist-info/METADATA
chessfluff-0.0.3.dist-info/RECORD
